fxn_llm/__init__.py
fxn_llm/locally.py
fxn_llm/version.py
fxn_llm-0.0.2.dist-info/LICENSE
fxn_llm-0.0.2.dist-info/METADATA
fxn_llm-0.0.2.dist-info/WHEEL
fxn_llm-0.0.2.dist-info/top_level.txt
fxn_llm-0.0.2.dist-info/RECORD
