Metadata-Version: 2.1
Name: fxn-llm
Version: 0.0.2
Summary: Use local LLMs in your Python apps, with GPU acceleration and zero dependencies.
Author-email: "NatML Inc." <hi@fxn.ai>
License: Apache License
Project-URL: Homepage, https://fxn.ai
Project-URL: Documentation, https://docs.fxn.ai
Project-URL: Source, https://github.com/fxnai/fxn-llm
Project-URL: Changelog, https://github.com/fxnai/fxn-llm/blob/main/Changelog.md
Classifier: Programming Language :: Python :: 3
Classifier: License :: OSI Approved :: Apache Software License
Classifier: Operating System :: OS Independent
Classifier: Topic :: Scientific/Engineering :: Image Recognition
Classifier: Topic :: Software Development :: Libraries
Requires-Python: >=3.10
License-File: LICENSE
Requires-Dist: fxn
Provides-Extra: anthropic
Requires-Dist: anthropic; extra == "anthropic"
Provides-Extra: openai
Requires-Dist: openai; extra == "openai"
